{
  "authorDailyContributionsMap": {
    "kokjoon97": [
      {
        "insertions": 1,
        "deletions": 1,
        "date": "2020-03-03",
        "commitResults": [
          {
            "hash": "e966b466dae8127f8fb2cef5203db18e61dc21d7",
            "messageTitle": "Update AboutUs",
            "messageBody": "",
            "insertions": 1,
            "deletions": 1
          }
        ]
      },
      {
        "insertions": 201,
        "deletions": 31,
        "date": "2020-03-06",
        "commitResults": [
          {
            "hash": "de900bed94dfcf3caf286c0b5c60e0f3423a816a",
            "messageTitle": "Add set budget and delete item function",
            "messageBody": "",
            "insertions": 138,
            "deletions": 6
          },
          {
            "hash": "dfee21dda63815ae9c157f4fe5ff3647073c1a73",
            "messageTitle": "Add JUnit test for Budget class",
            "messageBody": "",
            "insertions": 62,
            "deletions": 24
          },
          {
            "hash": "2b065bf8bf22169aafeb5672d343f7ca02b5cb63",
            "messageTitle": "Change command word \"bye\" to \"BYE\"",
            "messageBody": "",
            "insertions": 1,
            "deletions": 1
          }
        ]
      },
      {
        "insertions": 16,
        "deletions": 7,
        "date": "2020-03-08",
        "commitResults": [
          {
            "hash": "f8a984ff85d4ba2cd979cbd3ee73368b92249a27",
            "messageTitle": "Change execute method signature",
            "messageBody": "",
            "insertions": 16,
            "deletions": 7
          }
        ]
      }
    ],
    "JLoh579": [
      {
        "insertions": 1,
        "deletions": 1,
        "date": "2020-03-03",
        "commitResults": [
          {
            "hash": "d454148dbd93449d18d00ec58a43f8c9ea1f75c6",
            "messageTitle": "Add my name to AboutUs.md file",
            "messageBody": "",
            "insertions": 1,
            "deletions": 1
          }
        ]
      },
      {
        "insertions": 160,
        "deletions": 6,
        "date": "2020-03-06",
        "commitResults": [
          {
            "hash": "b69248716b643791a2f57d6a93d829e3ec1d7984",
            "messageTitle": "Add display list and clear list function",
            "messageBody": "",
            "insertions": 132,
            "deletions": 6
          },
          {
            "hash": "6c278bd8fcd27e83ceac8636756665ba75db4c91",
            "messageTitle": "Add JUnit tests for Budget class\u0027s getRemaining() method.",
            "messageBody": "",
            "insertions": 28,
            "deletions": 0
          }
        ]
      }
    ],
    "Shannonwje": [
      {
        "insertions": 1,
        "deletions": 1,
        "date": "2020-03-03",
        "commitResults": [
          {
            "hash": "3d5f4243b068ce26171daad3daf961a9755d80e1",
            "messageTitle": "Personalised Name on AboutUs",
            "messageBody": "",
            "insertions": 1,
            "deletions": 1
          }
        ]
      },
      {
        "insertions": 66,
        "deletions": 4,
        "date": "2020-03-06",
        "commitResults": [
          {
            "hash": "e28a67a5137cc4b2703f41ca0787a9045290bc79",
            "messageTitle": "Added a BoughtCommand",
            "messageBody": "",
            "insertions": 65,
            "deletions": 3
          },
          {
            "hash": "ced3033dcd6e72c188f72769793acb0876aaaf7f",
            "messageTitle": "Edited name of command",
            "messageBody": "",
            "insertions": 1,
            "deletions": 1
          }
        ]
      },
      {
        "insertions": 100,
        "deletions": 12,
        "date": "2020-03-07",
        "commitResults": [
          {
            "hash": "723b20e748d8a7d73d6a1ccbe543e330a2d52ffa",
            "messageTitle": "Added a Reset Budget Command",
            "messageBody": "",
            "insertions": 25,
            "deletions": 0
          },
          {
            "hash": "e8090cd0d94085deb8940d8debe33c8d5d5fca8e",
            "messageTitle": "Added an Unmark Command and renamed Bought Command to Mark Command",
            "messageBody": "",
            "insertions": 73,
            "deletions": 10
          },
          {
            "hash": "af0a45657ad2180b9a1f96f5eb013bd9a24cfab2",
            "messageTitle": "Edited the index bug",
            "messageBody": "",
            "insertions": 2,
            "deletions": 2
          }
        ]
      },
      {
        "insertions": 61,
        "deletions": 41,
        "date": "2020-03-08",
        "commitResults": [
          {
            "hash": "2bb162e4c7b9b283101a1def503e85640e7ceded",
            "messageTitle": "Edited to Coding Standard",
            "messageBody": "",
            "insertions": 8,
            "deletions": 8
          },
          {
            "hash": "92d15118299b098b14351e7abef634460c0d0677",
            "messageTitle": "Moved Command from Shopping List Class to Budget Class",
            "messageBody": "",
            "insertions": 22,
            "deletions": 5
          },
          {
            "hash": "2bddb275512042970cb109fc11a9823eafb75185",
            "messageTitle": "Added break to my Parser",
            "messageBody": "",
            "insertions": 1,
            "deletions": 0
          },
          {
            "hash": "2da3bcb30b6b1ea03f8eff6293ca5c627c8e52bb",
            "messageTitle": "Edited to fit group\u0027s coding style",
            "messageBody": "",
            "insertions": 8,
            "deletions": 6
          },
          {
            "hash": "be55e63af24c1cad2e6afdcc246f390ea75c77a4",
            "messageTitle": "Edited to fit group\u0027s coding style",
            "messageBody": "",
            "insertions": 12,
            "deletions": 6
          },
          {
            "hash": "940fdc4953193e4cab68dbf8534d52b0be604c66",
            "messageTitle": "Deleted unnecessary exceptions",
            "messageBody": "",
            "insertions": 10,
            "deletions": 16
          }
        ]
      }
    ],
    "jiajuinphoon": [
      {
        "insertions": 1,
        "deletions": 1,
        "date": "2020-03-03",
        "commitResults": [
          {
            "hash": "d5f696a03d0a4593e7cd5cf8237efa7a82f71e6d",
            "messageTitle": "Change on About Us",
            "messageBody": "",
            "insertions": 1,
            "deletions": 1
          }
        ]
      },
      {
        "insertions": 58,
        "deletions": 10,
        "date": "2020-03-06",
        "commitResults": [
          {
            "hash": "e7043140261e96e86d3608b9c6368edaa334b934",
            "messageTitle": "Implemented CommandAdd to add item.",
            "messageBody": "",
            "insertions": 46,
            "deletions": 4
          },
          {
            "hash": "c9ee38c07738cb5d10ae8d2cad53526459eb7d62",
            "messageTitle": "Small Changes for CommandAdd.",
            "messageBody": "",
            "insertions": 12,
            "deletions": 6
          }
        ]
      },
      {
        "insertions": 64,
        "deletions": 36,
        "date": "2020-03-08",
        "commitResults": [
          {
            "hash": "386e025a5912bd8afcb55615e040c7c294f0dcc1",
            "messageTitle": "Update for Add Command",
            "messageBody": "",
            "insertions": 53,
            "deletions": 30
          },
          {
            "hash": "4e8c2de52108008a455aa641e9810bd867a586cf",
            "messageTitle": "Updated Add Command",
            "messageBody": "",
            "insertions": 6,
            "deletions": 1
          },
          {
            "hash": "8851f342e33fe148c1a64e576b9a5ba51a8f3c12",
            "messageTitle": "Final update for Add Command",
            "messageBody": "",
            "insertions": 4,
            "deletions": 4
          },
          {
            "hash": "5b6dfadf35e33e9f3d6342d70f01191f398b33bd",
            "messageTitle": "Final update",
            "messageBody": "",
            "insertions": 1,
            "deletions": 1
          }
        ]
      }
    ],
    "trishaangelica": [
      {
        "insertions": 1,
        "deletions": 1,
        "date": "2020-03-03",
        "commitResults": [
          {
            "hash": "21da74acac2ff9f02a1c2f140c402f615241dc1b",
            "messageTitle": "Include my name (Trisha Labi) in AboutUs.md",
            "messageBody": "",
            "insertions": 1,
            "deletions": 1
          }
        ]
      },
      {
        "insertions": 206,
        "deletions": 8,
        "date": "2020-03-05",
        "commitResults": [
          {
            "hash": "66f33ec9bcfd9ca7f007142b0c2d77f8624142bb",
            "messageTitle": "Add skeleton classes (Done together as a team)",
            "messageBody": "",
            "insertions": 206,
            "deletions": 8
          }
        ]
      },
      {
        "insertions": 167,
        "deletions": 21,
        "date": "2020-03-06",
        "commitResults": [
          {
            "hash": "b6b191fa6ec7f3a4f2023503c9ddb364519e80f6",
            "messageTitle": "Edit item command added",
            "messageBody": "",
            "insertions": 12,
            "deletions": 0
          },
          {
            "hash": "d2b353411ca21153a0442b614eb3ca0072535a55",
            "messageTitle": "Edit item command Added",
            "messageBody": "",
            "insertions": 155,
            "deletions": 21
          }
        ]
      },
      {
        "insertions": 32,
        "deletions": 13,
        "date": "2020-03-08",
        "commitResults": [
          {
            "hash": "25f5a2633fd8a1bc9e04d3c1c05c301f3e801746",
            "messageTitle": "Slight changes made to: Error messages, initialization of data in duke, help command",
            "messageBody": "",
            "insertions": 29,
            "deletions": 8
          },
          {
            "hash": "fd03294b2d7151de3b0698e83c28f4456258067c",
            "messageTitle": "Removed unncessary colons",
            "messageBody": "",
            "insertions": 1,
            "deletions": 3
          },
          {
            "hash": "6f0c8a127edd526e2e01da44f7dddd17d4978b39",
            "messageTitle": "Changed method name",
            "messageBody": "",
            "insertions": 2,
            "deletions": 2
          }
        ]
      }
    ]
  },
  "authorFinalContributionMap": {
    "kokjoon97": 101,
    "JLoh579": 162,
    "Shannonwje": 161,
    "jiajuinphoon": 84,
    "trishaangelica": 377
  },
  "authorFileTypeContributionMap": {
    "kokjoon97": {
      "java": 100,
      "md": 1,
      "fxml": 0,
      "sh": 0,
      "bat": 0,
      "gradle": 0,
      "txt": 0
    },
    "JLoh579": {
      "java": 161,
      "md": 1,
      "fxml": 0,
      "sh": 0,
      "bat": 0,
      "gradle": 0,
      "txt": 0
    },
    "Shannonwje": {
      "java": 160,
      "md": 1,
      "fxml": 0,
      "sh": 0,
      "bat": 0,
      "gradle": 0,
      "txt": 0
    },
    "jiajuinphoon": {
      "java": 82,
      "md": 2,
      "fxml": 0,
      "sh": 0,
      "bat": 0,
      "gradle": 0,
      "txt": 0
    },
    "trishaangelica": {
      "java": 376,
      "md": 1,
      "fxml": 0,
      "sh": 0,
      "bat": 0,
      "gradle": 0,
      "txt": 0
    }
  },
  "authorContributionVariance": {
    "kokjoon97": 5762.6094,
    "JLoh579": 3004.0,
    "Shannonwje": 2203.4375,
    "jiajuinphoon": 1376.9375,
    "trishaangelica": 7246.1094
  },
  "authorDisplayNameMap": {
    "kokjoon97": "CS2113T-T13-1 TAN ..JOON",
    "JLoh579": "CS2113T-T13-1 LOH ..SHUA",
    "Shannonwje": "CS2113T-T13-1 WONG..NNON",
    "jiajuinphoon": "CS2113T-T13-1 PHOO..JUIN",
    "trishaangelica": "CS2113T-T13-1 LABI..GARA"
  }
}
